{
  "version": "1",
  "cognitoConfig": {
    "identityPoolName": "aiteacher109055a7f_identitypool_09055a7f",
    "allowUnauthenticatedIdentities": true,
    "resourceNameTruncated": "aiteac09055a7f",
    "userPoolName": "aiteacher109055a7f_userpool_09055a7f",
    "autoVerifiedAttributes": [
      "phone_number"
    ],
    "mfaConfiguration": "OFF",
    "mfaTypes": [
      "SMS Text Message"
    ],
    "smsAuthenticationMessage": "Your authentication code is {####}",
    "smsVerificationMessage": "{####}",
    "emailVerificationSubject": "Your verification code",
    "emailVerificationMessage": "Your verification code is {####}",
    "defaultPasswordPolicy": false,
    "passwordPolicyMinLength": 8,
    "passwordPolicyCharacters": [],
    "requiredAttributes": [
      "email"
    ],
    "aliasAttributes": [],
    "userpoolClientGenerateSecret": false,
    "userpoolClientRefreshTokenValidity": "30",
    "userpoolClientWriteAttributes": [
      "email"
    ],
    "userpoolClientReadAttributes": [
      "email"
    ],
    "userpoolClientLambdaRole": "aiteac09055a7f_userpoolclient_lambda_role",
    "userpoolClientSetAttributes": true,
    "sharedId": "09055a7f",
    "resourceName": "aiteacher109055a7f09055a7f",
    "authSelections": "identityPoolAndUserPool",
    "useDefault": "manual",
    "thirdPartyAuth": false,
    "usernameAttributes": [
      "email"
    ],
    "userPoolGroups": false,
    "adminQueries": false,
    "triggers": {},
    "hostedUI": false,
    "userPoolGroupList": [],
    "serviceName": "Cognito",
    "usernameCaseSensitive": false,
    "useEnabledMfas": true
  }
}